consolino/__init__.py
consolino-0.1.0.dist-info/METADATA
consolino-0.1.0.dist-info/WHEEL
consolino-0.1.0.dist-info/top_level.txt
consolino-0.1.0.dist-info/RECORD
