Metadata-Version: 2.4
Name: consolino
Version: 0.1.0
Summary: A simple Python library for cool console text effects and animations
Author-email: Tuo Nome <tuo@email.com>
Project-URL: Homepage, https://github.com/tuo-username/consolino
Keywords: console,animation,text-effects
Classifier: Programming Language :: Python :: 3
Classifier: Operating System :: OS Independent
Requires-Python: >=3.6
